repvgg_pytorch/__init__.py
repvgg_pytorch/repvgg.py
repvgg_pytorch/repvggplus.py
repvgg_pytorch/se_block.py
repvgg_pytorch-1.0.1.dist-info/LICENSE
repvgg_pytorch-1.0.1.dist-info/METADATA
repvgg_pytorch-1.0.1.dist-info/WHEEL
repvgg_pytorch-1.0.1.dist-info/top_level.txt
repvgg_pytorch-1.0.1.dist-info/RECORD
