Metadata-Version: 2.1
Name: repvgg-pytorch
Version: 1.0.1
Summary: RepVGG - Pytorch
Home-page: https://github.com/Asad-Ismail/repvgg-packaged
Author: Asad Ismail
Author-email: asadismaeel@gmail.com
License: MIT
Keywords: artificial intelligence,attention mechanism,image recognition
Classifier: Development Status :: 4 - Beta
Classifier: Intended Audience :: Developers
Classifier: Topic :: Scientific/Engineering :: Artificial Intelligence
Classifier: License :: OSI Approved :: MIT License
Classifier: Programming Language :: Python :: 3.8
License-File: LICENSE
Requires-Dist: einops (>=0.6.0)
Requires-Dist: torch (>=1.10)
Requires-Dist: torchvision
